<Attributes Version="35">
 <Attr name="ADSMouseSensitivity" value="1"/>
 <Attr name="AudioMasterVolume" value="1"/>
 <Attr name="AudioMusicVolume" value="0"/>
 <Attr name="AudioSfxVolume" value="0.62"/>
 <Attr name="AudioShipComputerSpeechVolume" value="0.7"/>
 <Attr name="AudioSimulationAnnouncerVolume" value="0.66"/>
 <Attr name="AudioSpeechVolume" value="1"/>
 <Attr name="AudioVOIPVolume" value="1"/>
 <Attr name="AutoZoomOnSelectedTargetStrength" value="1"/>
 <Attr name="Brightness" value="0.49"/>
 <Attr name="Contrast" value="0.51"/>
 <Attr name="ControlHintsEnabled" value="0"/>
 <Attr name="EnableCombatMusic" value="0"/>
 <Attr name="EnableFacewareSystemLive" value="0"/>
 <Attr name="EspZoneOuter" value="6.17"/>
 <Attr name="FOV" value="54.5107"/>
 <Attr name="FilmGrain" value="0"/>
 <Attr name="FlightCoupledDefaultOn" value="0"/>
 <Attr name="FlightGSafeDefaultOn" value="0"/>
 <Attr name="FlightSpeedLimiterDefaultOn" value="0"/>
 <Attr name="FoIPCameraSelection" value="561792202"/>
 <Attr name="GForceHeadBobScale" value="1"/>
 <Attr name="GForceZoomScale" value="0"/>
 <Attr name="Gamma" value="0.98"/>
 <Attr name="HeadTrackingFaceWareDeadzoneRotationPitch" value="10"/>
 <Attr name="HeadTrackingFaceWareDeadzoneRotationRoll" value="2"/>
 <Attr name="HeadTrackingFaceWareDeadzoneRotationYaw" value="10"/>
 <Attr name="HeadTrackingFaceWareSmoothingThreshold" value="1"/>
 <Attr name="HeadTrackingFacewarePitchMultiplier" value="8"/>
 <Attr name="HeadTrackingFacewareYawMultiplier" value="8"/>
 <Attr name="HeadtrackingDisableDuringADS" value="0"/>
 <Attr name="HeadtrackingEnableRollFPS" value="1"/>
 <Attr name="HeadtrackingGlobalSmoothingPosition" value="0"/>
 <Attr name="HeadtrackingGlobalSmoothingRotation" value="0"/>
 <Attr name="HeadtrackingInactivityTime" value="2"/>
 <Attr name="HeadtrackingSource" value="1"/>
 <Attr name="HeadtrackingToggle" value="1"/>
 <Attr name="Height" value="1080"/>
 <Attr name="HoldToggleZoom" value="1"/>
 <Attr name="IgnoreWindowFocus" value="1"/>
 <Attr name="InteractionHighlightMode" value="1"/>
 <Attr name="LeanToggle" value="0"/>
 <Attr name="LookAheadAutoTargetPadlockEnabled" value="1"/>
 <Attr name="LookAheadEnabledMGV" value="1"/>
 <Attr name="LookAheadStrengthForward" value="1"/>
 <Attr name="LookAheadStrengthHorizonAlignment" value="1"/>
 <Attr name="LookAheadStrengthHorizonLookAt" value="1"/>
 <Attr name="LookAheadStrengthJumpPointSpline" value="1"/>
 <Attr name="LookAheadStrengthMgvForward" value="1"/>
 <Attr name="LookAheadStrengthMgvHorizonAlignment" value="1"/>
 <Attr name="LookAheadStrengthMgvPitchYaw" value="1"/>
 <Attr name="LookAheadStrengthMgvVJoy" value="1"/>
 <Attr name="LookAheadStrengthQuantumBoostTarget" value="1"/>
 <Attr name="LookAheadStrengthRoll" value="1"/>
 <Attr name="LookAheadStrengthTargetSoft" value="1"/>
 <Attr name="LookAheadStrengthTurretForward" value="1"/>
 <Attr name="LookAheadStrengthTurretPitchYaw" value="1"/>
 <Attr name="LookAheadStrengthTurretVJoy" value="1"/>
 <Attr name="LookAheadStrengthVJoy" value="1"/>
 <Attr name="LookAheadStrengthVelocityVector" value="1"/>
 <Attr name="LookAheadStrengthYawPitch" value="1"/>
 <Attr name="ManualGimbalModeMgvDefault" value="0"/>
 <Attr name="OverscanBorderX" value="0"/>
 <Attr name="OverscanBorderY" value="0"/>
 <Attr name="PartyNameplateDistance" value="10045"/>
 <Attr name="PreferredAudioInputDeviceHash" value="-609086281"/>
 <Attr name="PreferredRegionId" value="2"/>
 <Attr name="Preset0" value=""/>
 <Attr name="Preset1" value=""/>
 <Attr name="Preset2" value=""/>
 <Attr name="Preset3" value=""/>
 <Attr name="Preset4" value=""/>
 <Attr name="Resolution" value="9"/>
 <Attr name="RestrictPartyInvitesNotifications" value="1"/>
 <Attr name="SalvageFreeGimbalLocksRotation" value="0"/>
 <Attr name="ScatterDist" value="1300"/>
 <Attr name="ShakeScale" value="1"/>
 <Attr name="ShowContactNeutralHostileNameplate" value="1"/>
 <Attr name="ShowEmissionsText" value="1"/>
 <Attr name="ShowHints" value="0"/>
 <Attr name="SpeedThrottleDefaultFixedSpeed" value="5"/>
 <Attr name="SysSpecPlanetVolumetricClouds" value="4"/>
 <Attr name="TerrainTessDistance" value="50"/>
 <Attr name="TobiiHeadPositionScale" value="3"/>
 <Attr name="TobiiHeadSensitivityRoll_Profile0" value="1"/>
 <Attr name="TobiiHeadSensitivityRoll_Profile1" value="1"/>
 <Attr name="TurretsEspDefaultOn" value="0"/>
 <Attr name="TurretsEspZoneOuter" value="8"/>
 <Attr name="VJoyShowDeadzone" value="0"/>
 <Attr name="VJoyVisibility" value="0"/>
 <Attr name="VSync" value="0"/>
 <Attr name="VelocityIndicatorDisplayMode" value="0"/>
 <Attr name="VelocityIndicatorDisplayType" value="2"/>
 <Attr name="VideoVolume" value="1"/>
 <Attr name="WeaponFallbackConvergenceDistance" value="1500"/>
 <Attr name="WeaponGimbalDefaultModeSpaceship" value="2"/>
 <Attr name="WeaponPipLeadLagType" value="1"/>
 <Attr name="Width" value="5760"/>
 <Attr name="WindowMode" value="2"/>
 <Attr name="selectedShipURN" value="urn:sc:global:entitlement:uuid:a1244555-bc7b-5b79-9a9f-a026a1a2a99e"/>
 <Attr name="selectedShipURN_EA_BattleRoyale" value="urn:sc:global:entitlement:uuid:35c3e5db-0a4e-5d09-bd6f-38738658a831"/>
 <Attr name="selectedShipURN_EA_ClassicRace" value="urn:sc:global:entitlement:uuid:a1244555-bc7b-5b79-9a9f-a026a1a2a99e"/>
 <Attr name="selectedShipURN_EA_Duel" value="urn:sc:global:entitlement:uuid:35c3e5db-0a4e-5d09-bd6f-38738658a831"/>
 <Attr name="selectedShipURN_EA_Elimination" value=""/>
 <Attr name="selectedShipURN_EA_ExperimentalMode_1" value="urn:sc:communal:entitlement::fdbd7d0d-75b0-4b0d-861d-340359e57112"/>
 <Attr name="selectedShipURN_EA_ExperimentalMode_3" value="urn:sc:communal:entitlement::b8a352bb-74a8-415b-9e08-77f684ac91b8"/>
 <Attr name="selectedShipURN_EA_ExperimentalMode_4" value="urn:sc:communal:entitlement::b8a352bb-74a8-415b-9e08-77f684ac91b8"/>
 <Attr name="selectedShipURN_EA_ExperimentalMode_6" value="urn:sc:communal:entitlement::96b11061-68ce-4896-9424-fc8804a410ae"/>
 <Attr name="selectedShipURN_EA_ExperimentalMode_7" value="urn:sc:communal:entitlement::fdbd7d0d-75b0-4b0d-861d-340359e57112"/>
 <Attr name="selectedShipURN_EA_ExperimentalMode_8" value="urn:sc:communal:entitlement::fdbd7d0d-75b0-4b0d-861d-340359e57112"/>
 <Attr name="selectedShipURN_EA_FreeFlight" value="urn:sc:global:entitlement:uuid:2b406650-71fc-5546-8387-e7e5b1b4f650"/>
 <Attr name="selectedShipURN_EA_PirateSwarm" value="urn:sc:global:entitlement:uuid:35c3e5db-0a4e-5d09-bd6f-38738658a831"/>
 <Attr name="selectedShipURN_EA_SquadronBattle" value="urn:sc:global:entitlement:uuid:35c3e5db-0a4e-5d09-bd6f-38738658a831"/>
 <Attr name="selectedShipURN_EA_VanduulSwarm" value="urn:sc:global:entitlement:uuid:a1244555-bc7b-5b79-9a9f-a026a1a2a99e"/>
</Attributes>
